freeze/__init__.py
freeze/metadata.py
freeze/parser.py
freeze/scanner.py
freeze/settings.py
freeze/sites.py
freeze/urls.py
freeze/views.py
freeze/writer.py
freeze/management/__init__.py
freeze/management/commands/__init__.py
freeze/management/commands/generate_static_site.py
freeze/templates/freeze/redirect.html
freeze/templates/freeze/js/local_urls.js
django_freeze-0.11.1.dist-info/LICENSE.txt
django_freeze-0.11.1.dist-info/METADATA
django_freeze-0.11.1.dist-info/WHEEL
django_freeze-0.11.1.dist-info/top_level.txt
django_freeze-0.11.1.dist-info/RECORD
