Metadata-Version: 2.1
Name: django-freeze
Version: 0.11.1
Summary: convert your dynamic django site to a static one with one line of code.
Author-email: Fabio Caccamo <fabio.caccamo@gmail.com>
Maintainer-email: Fabio Caccamo <fabio.caccamo@gmail.com>
License: The MIT License (MIT)
Project-URL: Homepage, https://github.com/fabiocaccamo/django-freeze
Project-URL: Download, https://github.com/fabiocaccamo/django-freeze/releases
Project-URL: Documentation, https://github.com/fabiocaccamo/django-freeze#readme
Project-URL: Issues, https://github.com/fabiocaccamo/django-freeze/issues
Project-URL: Funding, https://github.com/sponsors/fabiocaccamo/
Project-URL: Twitter, https://twitter.com/fabiocaccamo
Keywords: django,freeze,static,site,generator,generate,convert,export,download,zip
Classifier: Development Status :: 5 - Production/Stable
Classifier: Environment :: Web Environment
Classifier: Framework :: Django
Classifier: Framework :: Django :: 3.0
Classifier: Framework :: Django :: 3.1
Classifier: Framework :: Django :: 3.2
Classifier: Framework :: Django :: 4.0
Classifier: Framework :: Django :: 4.1
Classifier: Framework :: Django :: 4.2
Classifier: Framework :: Django :: 5.0
Classifier: Intended Audience :: Developers
Classifier: License :: OSI Approved :: MIT License
Classifier: Natural Language :: English
Classifier: Operating System :: OS Independent
Classifier: Programming Language :: Python :: 3.8
Classifier: Programming Language :: Python :: 3.9
Classifier: Programming Language :: Python :: 3.10
Classifier: Programming Language :: Python :: 3.11
Classifier: Programming Language :: Python :: 3.12
Classifier: Topic :: Software Development :: Build Tools
License-File: LICENSE.txt
Requires-Dist: beautifulsoup4 >=4.11.1
Requires-Dist: requests >=2.28.1
Requires-Dist: xmltodict >=0.13.0
